statisticalrl_environments/__init__.py
statisticalrl_environments/fulldemo.py
statisticalrl_environments/register.py
statisticalrl_environments/MABs/Distributions.py
statisticalrl_environments/MABs/MDPtoMAB_wrapper.py
statisticalrl_environments/MABs/StochasticBandits.py
statisticalrl_environments/MABs/__init__.py
statisticalrl_environments/MABs/rendering/__init__.py
statisticalrl_environments/MABs/rendering/textRenderer.py
statisticalrl_environments/MDPs_discrete/__init__.py
statisticalrl_environments/MDPs_discrete/gymWrapper.py
statisticalrl_environments/MDPs_discrete/utils.py
statisticalrl_environments/MDPs_discrete/envs/RandomMDP.py
statisticalrl_environments/MDPs_discrete/envs/RiverSwim.py
statisticalrl_environments/MDPs_discrete/envs/ThreeStateMDP.py
statisticalrl_environments/MDPs_discrete/envs/__init__.py
statisticalrl_environments/MDPs_discrete/envs/GridWorld/__init__.py
statisticalrl_environments/MDPs_discrete/envs/GridWorld/gridworld.py
statisticalrl_environments/MDPs_discrete/envs/GridWorld/envs/__init__.py
statisticalrl_environments/MDPs_discrete/envs/GridWorld/rendering/__init__.py
statisticalrl_environments/MDPs_discrete/envs/GridWorld/rendering/pyplotRenderer.py
statisticalrl_environments/MDPs_discrete/envs/GridWorld/rendering/textRenderer.py
statisticalrl_environments/MDPs_discrete/rendering/__init__.py
statisticalrl_environments/MDPs_discrete/rendering/networkxRenderer.py
statisticalrl_environments/MDPs_discrete/rendering/pydotRenderer.py
statisticalrl_environments/MDPs_discrete/rendering/textRenderer.py
statisticalrl_environments-2.2507.dist-info/licenses/LICENSE
statisticalrl_environments-2.2507.dist-info/METADATA
statisticalrl_environments-2.2507.dist-info/WHEEL
statisticalrl_environments-2.2507.dist-info/top_level.txt
statisticalrl_environments-2.2507.dist-info/RECORD
